README.md
setup.cfg
setup.py
players_amp/__init__.py
players_amp/debug.py
players_amp/main.py
players_amp/setserver.py
players_amp.egg-info/PKG-INFO
players_amp.egg-info/SOURCES.txt
players_amp.egg-info/dependency_links.txt
players_amp.egg-info/entry_points.txt
players_amp.egg-info/requires.txt
players_amp.egg-info/top_level.txt
players_amp/api_functions/GetInstances.py
players_amp/api_functions/GetUpdates.py
players_amp/api_functions/Login.py
players_amp/api_functions/Logout.py
players_amp/api_functions/__init__.py