Metadata-Version: 1.1
Name: players-amp
Version: 2.34
Summary: a little tool written in phyton to count all the active players on your AMP managed game server
Home-page: https://github.com/R0b95/player_amp
Author: Strolch
Author-email: hello.circles@gmail.com
License: MIT
Download-URL: https://github.com/R0b95/players_amp/archive/2.0.tar.gz
Keywords: AMP,UserCount,ActiveUser,ActivePlayer
Platform: UNKNOWN
Classifier: Development Status :: 4 - Beta
Classifier: Intended Audience :: Developers
Classifier: Topic :: Software Development :: Build Tools
Classifier: License :: OSI Approved :: MIT License
Classifier: Programming Language :: Python
